{"version":1,"resource":"file:///home/epistelmoz/projects/leetCodeTS/src/10.regularExpression.ts","entries":[{"id":"TVGp.ts","timestamp":1667913981191},{"id":"Lmy7.ts","timestamp":1667914012668},{"id":"Ars2.ts","timestamp":1667914044128},{"id":"DW7p.ts","timestamp":1667914072971},{"id":"Y70s.ts","timestamp":1667914087564},{"id":"KosV.ts","timestamp":1667914132764},{"id":"dP7w.ts","timestamp":1667914166070},{"id":"t3fM.ts","timestamp":1667914207463},{"id":"mD0l.ts","timestamp":1667914232883},{"id":"uyKG.ts","timestamp":1667914257520},{"id":"Eexa.ts","timestamp":1667914268290},{"id":"0z92.ts","timestamp":1667914283910},{"id":"OKIS.ts","timestamp":1668412550064},{"id":"AVZo.ts","timestamp":1668412565954},{"id":"1Axr.ts","timestamp":1668412584944},{"id":"roSp.ts","timestamp":1668412623287},{"id":"HAPH.ts","timestamp":1668412681446},{"id":"k4lj.ts","timestamp":1668412782572},{"id":"umP3.ts","timestamp":1668412798776},{"id":"wOsa.ts","timestamp":1668412810232},{"id":"3Dhc.ts","timestamp":1668412829939},{"id":"u8MN.ts","timestamp":1668412905855},{"id":"3i7c.ts","source":"undoRedo.source","timestamp":1668412907125},{"id":"FVdc.ts","timestamp":1668412957212},{"id":"UgPz.ts","timestamp":1668412985475},{"id":"zsQD.ts","timestamp":1668413948879},{"id":"KtJ8.ts","timestamp":1668413972529},{"id":"GvuZ.ts","timestamp":1668414015512},{"id":"B4ye.ts","timestamp":1668414037739},{"id":"1S0n.ts","timestamp":1668414054125},{"id":"Vwr5.ts","timestamp":1668414090425},{"id":"7Wl2.ts","timestamp":1668414111845},{"id":"ibAU.ts","timestamp":1668414149655},{"id":"ReGY.ts","timestamp":1668414187405},{"id":"3ymq.ts","source":"undoRedo.source","timestamp":1668414226591},{"id":"XgIh.ts","timestamp":1668414324987},{"id":"gF6U.ts","timestamp":1668414363094},{"id":"h3sz.ts","timestamp":1668414403430},{"id":"ycsA.ts","timestamp":1668414429950},{"id":"XwmC.ts","timestamp":1668414442860},{"id":"OJii.ts","timestamp":1668414497806},{"id":"RQQl.ts","timestamp":1668414522050},{"id":"c9Zv.ts","timestamp":1668414557599},{"id":"WgyA.ts","timestamp":1668414572429},{"id":"SlBz.ts","source":"undoRedo.source","timestamp":1668414575386},{"id":"tSHD.ts","timestamp":1668414580986},{"id":"znMv.ts","timestamp":1668414641039},{"id":"NfIm.ts","source":"undoRedo.source","timestamp":1668414649182},{"id":"BGRO.ts","timestamp":1668414653379},{"id":"mqXd.ts","timestamp":1668414682255}]}