{"version":1,"resource":"file:///home/epistelmoz/note/CompilersInterpreters/5-Yacc-Bison.md","entries":[{"id":"7hRq.md","timestamp":1665676720828},{"id":"wosC.md","timestamp":1665676786915},{"id":"62EB.md","timestamp":1665676823635},{"id":"QdsW.md","timestamp":1665676840998},{"id":"comn.md","timestamp":1665676874304},{"id":"f0yc.md","timestamp":1665676940951},{"id":"vCW0.md","timestamp":1665677020983},{"id":"c4jb.md","timestamp":1665677055090},{"id":"I0yw.md","timestamp":1665677072080},{"id":"k4ek.md","timestamp":1665678540855},{"id":"XgVX.md","timestamp":1665678583895},{"id":"beh8.md","timestamp":1665678611585},{"id":"nvnM.md","timestamp":1665678642615},{"id":"ugVb.md","timestamp":1665678659288},{"id":"fV9E.md","timestamp":1665678680324},{"id":"yLvz.md","timestamp":1665678692194},{"id":"bWaI.md","timestamp":1665678709168},{"id":"kA5K.md","timestamp":1665678789577},{"id":"l7nC.md","timestamp":1665678863993},{"id":"E6Rl.md","timestamp":1665678965913},{"id":"xiZk.md","timestamp":1665679081505},{"id":"U60e.md","timestamp":1665679125339},{"id":"QYfH.md","timestamp":1665679172338},{"id":"0Kp0.md","timestamp":1665679235105},{"id":"UleA.md","timestamp":1665679388030},{"id":"1083.md","timestamp":1665679404100},{"id":"j4bk.md","timestamp":1665679438157},{"id":"FuU6.md","timestamp":1665679454740},{"id":"C1n7.md","timestamp":1665679476833},{"id":"ahiK.md","timestamp":1665679509226},{"id":"OgHF.md","timestamp":1665679519266},{"id":"G4eh.md","timestamp":1665679595456},{"id":"wQ1P.md","timestamp":1665679657572},{"id":"E8UL.md","timestamp":1665679670452},{"id":"qG9W.md","timestamp":1665679700255},{"id":"jAIK.md","timestamp":1665679728255},{"id":"Q5HV.md","timestamp":1665679798275},{"id":"YGne.md","timestamp":1665679832085},{"id":"zM3t.md","timestamp":1665679863195},{"id":"EJZ0.md","timestamp":1665679879821},{"id":"X50Q.md","timestamp":1665679913284},{"id":"vQRO.md","timestamp":1665680025947},{"id":"hwrc.md","timestamp":1665680065840},{"id":"RfzP.md","timestamp":1665680298819},{"id":"Ly50.md","timestamp":1665680361392},{"id":"0c5j.md","timestamp":1665680456075},{"id":"USUo.md","timestamp":1665680494161},{"id":"GKcg.md","timestamp":1665680525201},{"id":"cKYC.md","timestamp":1665680536311},{"id":"XWXX.md","timestamp":1665680570171}]}